text_fabric-13.0.19.dist-info/licenses/LICENSE
tf/__init__.py
tf/app.py
tf/capable.py
tf/cheatsheet.py
tf/clean.py
tf/fabric.py
tf/lib.py
tf/parameters.py
tf/zip.py
tf/about/__init__.py
tf/about/annotate.py
tf/about/annotateBrowser.py
tf/about/apps.py
tf/about/background.py
tf/about/browser.py
tf/about/clientmanual.py
tf/about/code.py
tf/about/corpora.py
tf/about/datamodel.py
tf/about/datasharing.py
tf/about/displaydesign.py
tf/about/faq.py
tf/about/fileformats.py
tf/about/install.py
tf/about/manual.py
tf/about/optimizations.py
tf/about/releases.py
tf/about/releasesold.py
tf/about/searchdesign.py
tf/about/searchusage.py
tf/about/stam.py
tf/about/tests.py
tf/about/use.py
tf/about/usefunc.py
tf/about/variants.py
tf/about/volumes.py
tf/advanced/__init__.py
tf/advanced/annotate.py
tf/advanced/app.py
tf/advanced/condense.py
tf/advanced/data.py
tf/advanced/display.py
tf/advanced/find.py
tf/advanced/helpers.py
tf/advanced/highlight.py
tf/advanced/interchange.py
tf/advanced/links.py
tf/advanced/options.py
tf/advanced/render.py
tf/advanced/repo.py
tf/advanced/search.py
tf/advanced/sections.py
tf/advanced/settings.py
tf/advanced/tables.py
tf/advanced/text.py
tf/advanced/unravel.py
tf/advanced/volumes.py
tf/advanced/zipdata.py
tf/browser/__init__.py
tf/browser/command.py
tf/browser/html.py
tf/browser/kernel.py
tf/browser/serve.py
tf/browser/servelib.py
tf/browser/start.py
tf/browser/web.py
tf/browser/wrap.py
tf/browser/ner/form.py
tf/browser/ner/fragments.py
tf/browser/ner/request.py
tf/browser/ner/serve.py
tf/browser/ner/web.py
tf/browser/ner/websettings.py
tf/browser/ner/static/base.css
tf/browser/ner/static/index.css
tf/browser/ner/static/tool.js
tf/browser/ner/templates/ner/index.html
tf/browser/static/base.css
tf/browser/static/chars.js
tf/browser/static/colors.css
tf/browser/static/dans.png
tf/browser/static/display.css
tf/browser/static/export.css
tf/browser/static/favicon.ico
tf/browser/static/fontawesome.css
tf/browser/static/fonts.css
tf/browser/static/highlight.css
tf/browser/static/huc.png
text_fabric-13.0.19.dist-info/METADATA
text_fabric-13.0.19.dist-info/WHEEL
text_fabric-13.0.19.dist-info/entry_points.txt
text_fabric-13.0.19.dist-info/top_level.txt
text_fabric-13.0.19.dist-info/RECORD
