Metadata-Version: 2.4
Name: text-fabric
Version: 13.0.19
Summary: Processor and browser for annotated text corpora
Home-page: https://github.com/annotation/text-fabric
Author: Dirk Roorda
Author-email: droorda.it@icloud.com
License: MIT
Keywords: text,linguistics,database,graph,hebrew,bible,peshitta,quran,cuneiform,uruk,greek,syriac,akkadian,babylonian
Classifier: Development Status :: 4 - Beta
Classifier: Environment :: Other Environment
Classifier: Framework :: Jupyter
Classifier: Intended Audience :: Developers
Classifier: Intended Audience :: Education
Classifier: Intended Audience :: Religion
Classifier: Intended Audience :: Science/Research
Classifier: Natural Language :: English
Classifier: Natural Language :: Hebrew
Classifier: Natural Language :: Greek
Classifier: Operating System :: MacOS :: MacOS X
Classifier: Operating System :: Microsoft :: Windows :: Windows 10
Classifier: Operating System :: POSIX :: Linux
Classifier: Programming Language :: Python :: 3 :: Only
Classifier: Programming Language :: Python :: Implementation :: CPython
Classifier: Programming Language :: JavaScript
Classifier: Topic :: Religion
Classifier: Topic :: Scientific/Engineering :: Information Analysis
Classifier: Topic :: Sociology :: History
Classifier: Topic :: Text Processing :: Filters
Classifier: Topic :: Text Processing :: Linguistic
Classifier: Topic :: Text Processing :: Markup
Requires-Python: >=3.9.0
License-File: LICENSE
Requires-Dist: wheel
Requires-Dist: markdown>=3.4.1
Requires-Dist: ipython
Requires-Dist: pyyaml>=5.3
Requires-Dist: flask
Requires-Dist: requests
Provides-Extra: github
Requires-Dist: pygithub>=1.57; extra == "github"
Provides-Extra: gitlab
Requires-Dist: python-gitlab>=3.5.0; extra == "gitlab"
Provides-Extra: all
Requires-Dist: pygithub>=1.57; extra == "all"
Requires-Dist: python-gitlab>=3.5.0; extra == "all"
Dynamic: license-file
